[
  {
    "text": "Menu Heading",
    "heading": "true",
    "translate": "sidebar.heading.HEADER"
  },
  {
    "text": "Over View",
    "sref": "app.overview",
    "icon": "icon-home",
    "translate": "sidebar.nav.OVERVIEW"
  },
  {
    "text": "Inventory",
    "sref": "app.inventory",
    "icon": "icon-grid",
    "translate": "sidebar.nav.INVENTORY"
  },
  {
    "text": "Maintenance",
    "sref": "app.maintenance",
    "alert": "5" ,
    "label": "label label-info",
    "icon": "icon-calendar",
    "translate": "sidebar.nav.MAINTENANCE"
  },
  {
    "text": "Moving / Storage",
    "sref": "app.moving",
    "icon": "fa fa-truck",
    "translate": "sidebar.nav.MOVING"
  },
  {
    "text": "Money",
    "sref": "#",
    "icon": "fa fa-dollar",
    "submenu": [
      { "text": "Home Equity",
        "sref": "app.equity",
        "icon": "icon-home",
        "translate": "sidebar.nav.money.EQUITY"
      },
      { "text": "Sales",
        "sref": "app.sales",
        "icon": "icon-tag",
        "translate": "sidebar.nav.money.SALES"
      },
      { "text": "Donations",
        "sref": "app.donations",
        "icon": "icon-heart",
        "translate": "sidebar.nav.money.DONATIONS"
      },
      { "text": "Sharing",
        "sref": "app.sharing",
        "icon": "icon-share",
        "translate": "sidebar.nav.money.SHARING"
      }
    ],
    "translate": "sidebar.nav.money.MONEY"
  }
]
